{
  "_id": "daSEOLpfyiHMzXVU",
  "_key": "!items!daSEOLpfyiHMzXVU",
  "folder": null,
  "sort": 0,
  "flags": {},
  "name": "Le Dragon de l'Ouest",
  "type": "aspect",
  "img": "icons/svg/sun.svg",
  "system": {
    "voie": "Voie des Huit Roi-Dragons",
    "niveau": 0,
    "description": "« Celui qui voit tout ». Autres noms : le Tigre Blanc, Komoku-ten, Byakko, le Gardien de l'Ouest. Point cardinal : Ouest. Saison : Automne. Élément : Métal. Couleur : Blanc. Domaines : Clairvoyance ; Pureté. Le Dragon de l'Ouest voit le mal où qu'il se cache : ses adeptes incarnent la pureté dans sa forme la plus absolue, respectent et font respecter tous les tabous et chassent la souillure (kegare). Ironiquement, ils sont aussi les plus nombreux à succomber à la corruption du Yomi s'ils ne parviennent pas à se purifier."
  }
}
